LICENSE
MANIFEST.in
README.md
setup.py
argonaut/__init__.py
argonaut/callbacks/Curriculum.py
argonaut/callbacks/CyclicLR.py
argonaut/callbacks/EpochStepLR.py
argonaut/callbacks/MultiTask.py
argonaut/callbacks/PlateauLR.py
argonaut/callbacks/__init__.py
argonaut/components/__init__.py
argonaut/components/heads.py
argonaut/datasets/__init__.py
argonaut/datasets/cifar.py
argonaut/datasets/cub200.py
argonaut/datasets/face_scrub.py
argonaut/datasets/fashion_mnist.py
argonaut/datasets/mnist.py
argonaut/datasets/not_mnist.py
argonaut/datasets/pipeline.py
argonaut/datasets/svhn.py
argonaut/datasets/traffic_signs.py
argonaut/datasets/utils.py
argonaut/datasets/transformer/__init__.py
argonaut/datasets/transformer/augmentation_transformer.py
argonaut/datasets/transformer/complexity_transformer.py
argonaut/datasets/transformer/image_transformer.py
argonaut/datasets/transformer/transformer.py
argonaut/experiments/__init__.py
argonaut/experiments/baseline.py
argonaut/experiments/experiment.py
argonaut/models/__init__.py
argonaut/models/alexnet.py
argonaut/models/densenet.py
argonaut/models/resnetv2.py
argonaut/models/simple.py
argonaut/models/vgg16.py
argonaut/utils/__init__.py
argonaut/utils/execute.py
argonaut/utils/utils.py
argonaut/utils/visualization.py
tf_argonaut.egg-info/PKG-INFO
tf_argonaut.egg-info/SOURCES.txt
tf_argonaut.egg-info/dependency_links.txt
tf_argonaut.egg-info/entry_points.txt
tf_argonaut.egg-info/not-zip-safe
tf_argonaut.egg-info/requires.txt
tf_argonaut.egg-info/top_level.txt