Metadata-Version: 2.1
Name: tf-argonaut
Version: 0.2.0
Summary: Tensorflow Experimentation Pipeline
Home-page: https://github.com/felixnext/tf-argonaut
Author: Felix Geilert
License: Apache License 2.0
Keywords: tensorflow experimentation computervision
Platform: UNKNOWN
